gjp_models/__init__.py
gjp_models/models.py
gjp_models-0.1.10.dist-info/METADATA
gjp_models-0.1.10.dist-info/WHEEL
gjp_models-0.1.10.dist-info/RECORD
