Metadata-Version: 2.3
Name: gjp-models
Version: 0.1.10
Summary: 
Author: giannisevagorou
Author-email: giannis.evagorou@macrocosmos.ai
Requires-Python: >=3.11,<3.14
Classifier: Programming Language :: Python :: 3
Classifier: Programming Language :: Python :: 3.11
Classifier: Programming Language :: Python :: 3.12
Classifier: Programming Language :: Python :: 3.13
Requires-Dist: numpy (>=1.21.4,<3)
Requires-Dist: pydantic (>=2.3,<3)
